yt_concate/__init__.py
yt_concate/main.py
yt_concate/settings.py
yt_concate/utils.py
yt_concate/model/__init__.py
yt_concate/model/catch_yto.py
yt_concate/model/yto.py
yt_concate/pipeline/__init__.py
yt_concate/pipeline/pipeline.py
yt_concate/pipeline/steps/__init__.py
yt_concate/pipeline/steps/download_captions.py
yt_concate/pipeline/steps/download_video.py
yt_concate/pipeline/steps/edit_video.py
yt_concate/pipeline/steps/get_v_links.py
yt_concate/pipeline/steps/initialize_yto.py
yt_concate/pipeline/steps/postflight.py
yt_concate/pipeline/steps/preflight.py
yt_concate/pipeline/steps/read_captions.py
yt_concate/pipeline/steps/search.py
yt_concate/pipeline/steps/step.py
york_yt_concate-0.1.1.dist-info/LICENSE
york_yt_concate-0.1.1.dist-info/METADATA
york_yt_concate-0.1.1.dist-info/WHEEL
york_yt_concate-0.1.1.dist-info/top_level.txt
york_yt_concate-0.1.1.dist-info/RECORD
