Metadata-Version: 2.1
Name: york-yt-concate
Version: 0.1.1
Summary: Produce a concatenated video of clips that mentioned a word from YouTube channel
Home-page: https://github.com/smallwater94/yt-concat
Author: York Wu
Author-email: smallwater94@gmail.com
License: MIT
Platform: UNKNOWN
Classifier: License :: OSI Approved :: MIT License
Classifier: Programming Language :: Python
Classifier: Programming Language :: Python :: 3
Classifier: Programming Language :: Python :: 3.6
Classifier: Programming Language :: Python :: Implementation :: CPython
Classifier: Programming Language :: Python :: Implementation :: PyPy
Requires-Python: >=3.9.0
Requires-Dist: moviepy
Requires-Dist: pytube
Requires-Dist: requests
Requires-Dist: urllib3
Requires-Dist: python-dotenv
Requires-Dist: youtube-dl
Requires-Dist: youtube-transcript-api
